<?xml version="1.0" encoding="utf-8" ?>
<dwsync>
<file name="banner-hero.php" server="vietseo.org/public_html/" local="133637677003740843" remote="133418628000000000" Dst="0" />
<file name="banner-project-description.php" server="vietseo.org/public_html/" local="133637677003740843" remote="133418628000000000" Dst="0" />
<file name="cta-content-image-on-right.php" server="vietseo.org/public_html/" local="133637677004053215" remote="133418628000000000" Dst="0" />
<file name="cta-pricing.php" server="vietseo.org/public_html/" local="133637677004053215" remote="133436772000000000" Dst="0" />
<file name="cta-rsvp.php" server="vietseo.org/public_html/" local="133637677004053215" remote="133418628000000000" Dst="0" />
<file name="cta-services-image-left.php" server="vietseo.org/public_html/" local="133637677004209471" remote="133425540000000000" Dst="0" />
<file name="cta-subscribe-centered.php" server="vietseo.org/public_html/" local="133637677004365769" remote="133418628000000000" Dst="0" />
<file name="footer-centered-logo-nav.php" server="vietseo.org/public_html/" local="133637677004380866" remote="133418628000000000" Dst="0" />
<file name="footer-colophon-3-col.php" server="vietseo.org/public_html/" local="133637677004526046" remote="133418628000000000" Dst="0" />
<file name="footer.php" server="vietseo.org/public_html/" local="133637677004526046" remote="133521701400000000" Dst="0" />
<file name="gallery-full-screen-image.php" server="vietseo.org/public_html/" local="133637677004682444" remote="133418628000000000" Dst="0" />
<file name="gallery-offset-images-grid-2-col.php" server="vietseo.org/public_html/" local="133637677004682444" remote="133418628000000000" Dst="0" />
<file name="gallery-offset-images-grid-3-col.php" server="vietseo.org/public_html/" local="133637677004838747" remote="133418628000000000" Dst="0" />
<file name="gallery-offset-images-grid-4-col.php" server="vietseo.org/public_html/" local="133637677004838747" remote="133418628000000000" Dst="0" />
<file name="gallery-project-layout.php" server="vietseo.org/public_html/" local="133637677004994977" remote="133418628000000000" Dst="0" />
<file name="hidden-404.php" server="vietseo.org/public_html/" local="133637677005151183" remote="133418628000000000" Dst="0" />
<file name="hidden-comments.php" server="vietseo.org/public_html/" local="133637677005151183" remote="133418628000000000" Dst="0" />
<file name="hidden-no-results.php" server="vietseo.org/public_html/" local="133637677005307611" remote="133418628000000000" Dst="0" />
<file name="hidden-portfolio-hero.php" server="vietseo.org/public_html/" local="133637677005382792" remote="133499484000000000" Dst="0" />
<file name="hidden-post-meta.php" server="vietseo.org/public_html/" local="133637677005467884" remote="133418628000000000" Dst="0" />
<file name="hidden-post-navigation.php" server="vietseo.org/public_html/" local="133637677005467884" remote="133418628000000000" Dst="0" />
<file name="hidden-sidebar.php" server="vietseo.org/public_html/" local="133637677005624210" remote="133436772000000000" Dst="0" />
<file name="page-about-business.php" server="vietseo.org/public_html/" local="133637677005780462" remote="133517691000000000" Dst="0" />
<file name="page-home-business.php" server="vietseo.org/public_html/" local="133637677006092965" remote="133517691000000000" Dst="0" />
<file name="page-home-portfolio-gallery.php" server="vietseo.org/public_html/" local="133637677006565793" remote="133517691000000000" Dst="0" />
<file name="hidden-search.php" server="vietseo.org/public_html/" local="133637677006565793" remote="133418628000000000" Dst="0" />
<file name="page-home-portfolio.php" server="vietseo.org/public_html/" local="133637677006878330" remote="133517691000000000" Dst="0" />
<file name="page-newsletter-landing.php" server="vietseo.org/public_html/" local="133637677006878330" remote="133517691000000000" Dst="0" />
<file name="page-home-blogging.php" server="vietseo.org/public_html/" local="133637677007034565" remote="133517691000000000" Dst="0" />
<file name="page-portfolio-overview.php" server="vietseo.org/public_html/" local="133637677007034565" remote="133517691000000000" Dst="0" />
<file name="page-rsvp-landing.php" server="vietseo.org/public_html/" local="133637677007191474" remote="133517691000000000" Dst="0" />
<file name="posts-1-col.php" server="vietseo.org/public_html/" local="133637677007347161" remote="133418628000000000" Dst="0" />
<file name="posts-3-col.php" server="vietseo.org/public_html/" local="133637677007387234" remote="133418628000000000" Dst="0" />
<file name="posts-images-only-3-col.php" server="vietseo.org/public_html/" local="133637677007507304" remote="133418628000000000" Dst="0" />
<file name="posts-grid-2-col.php" server="vietseo.org/public_html/" local="133637677008449103" remote="133418628000000000" Dst="0" />
<file name="posts-images-only-offset-4-col.php" server="vietseo.org/public_html/" local="133637677008449103" remote="133418628000000000" Dst="0" />
<file name="posts-list.php" server="vietseo.org/public_html/" local="133637677008605467" remote="133431588000000000" Dst="0" />
<file name="team-4-col.php" server="vietseo.org/public_html/" local="133637677008605467" remote="133418628000000000" Dst="0" />
<file name="template-archive-blogging.php" server="vietseo.org/public_html/" local="133637677008761708" remote="133418628000000000" Dst="0" />
<file name="template-archive-portfolio.php" server="vietseo.org/public_html/" local="133637677008917962" remote="133418628000000000" Dst="0" />
<file name="template-home-blogging.php" server="vietseo.org/public_html/" local="133637677008917962" remote="133418628000000000" Dst="0" />
<file name="template-home-business.php" server="vietseo.org/public_html/" local="133637677008917962" remote="133431588000000000" Dst="0" />
<file name="template-home-portfolio.php" server="vietseo.org/public_html/" local="133637677009074231" remote="133431588000000000" Dst="0" />
<file name="template-index-blogging.php" server="vietseo.org/public_html/" local="133637677009074231" remote="133418628000000000" Dst="0" />
<file name="template-index-portfolio.php" server="vietseo.org/public_html/" local="133637677009230477" remote="133418628000000000" Dst="0" />
<file name="template-search-blogging.php" server="vietseo.org/public_html/" local="133637677009391781" remote="133425540000000000" Dst="0" />
<file name="template-search-portfolio.php" server="vietseo.org/public_html/" local="133637677009391781" remote="133418628000000000" Dst="0" />
<file name="template-single-portfolio.php" server="vietseo.org/public_html/" local="133637677009703334" remote="133418628000000000" Dst="0" />
<file name="testimonial-centered.php" server="vietseo.org/public_html/" local="133637677009703334" remote="133418628000000000" Dst="0" />
<file name="text-alternating-images.php" server="vietseo.org/public_html/" local="133637677009859526" remote="133418628000000000" Dst="0" />
<file name="text-centered-statement-small.php" server="vietseo.org/public_html/" local="133637677009859526" remote="133418628000000000" Dst="0" />
<file name="text-centered-statement.php" server="vietseo.org/public_html/" local="133637677010015693" remote="133418628000000000" Dst="0" />
<file name="text-faq.php" server="vietseo.org/public_html/" local="133637677010171959" remote="133436772000000000" Dst="0" />
<file name="text-feature-grid-3-col.php" server="vietseo.org/public_html/" local="133637677010171959" remote="133418628000000000" Dst="0" />
<file name="text-project-details.php" server="vietseo.org/public_html/" local="133637677010328678" remote="133418628000000000" Dst="0" />
<file name="text-title-left-image-right.php" server="vietseo.org/public_html/" local="133637677010488804" remote="133418628000000000" Dst="0" />
</dwsync>