<?xml version="1.0" encoding="utf-8" ?>
<dwsync>
<file name="class-IXR-base64.php" server="vietseo.org/public_html/" local="133637677113315718" remote="131166180000000000" Dst="0" />
<file name="class-IXR-client.php" server="vietseo.org/public_html/" local="133637677113471839" remote="132379236000000000" Dst="0" />
<file name="class-IXR-clientmulticall.php" server="vietseo.org/public_html/" local="133637677113586908" remote="132379236000000000" Dst="0" />
<file name="class-IXR-date.php" server="vietseo.org/public_html/" local="133637677113631958" remote="132031908000000000" Dst="0" />
<file name="class-IXR-error.php" server="vietseo.org/public_html/" local="133637677113789072" remote="131166180000000000" Dst="0" />
<file name="class-IXR-introspectionserver.php" server="vietseo.org/public_html/" local="133637677113789072" remote="131166180000000000" Dst="0" />
<file name="class-IXR-message.php" server="vietseo.org/public_html/" local="133637677113789072" remote="133185348000000000" Dst="0" />
<file name="class-IXR-request.php" server="vietseo.org/public_html/" local="133637677113944542" remote="131166180000000000" Dst="0" />
<file name="class-IXR-server.php" server="vietseo.org/public_html/" local="133637677113944542" remote="132661764000000000" Dst="0" />
<file name="class-IXR-value.php" server="vietseo.org/public_html/" local="133637677114100792" remote="131166180000000000" Dst="0" />
</dwsync>